odoo/addons/stock_secondary_unit_weighing/README.rst
odoo/addons/stock_secondary_unit_weighing/__init__.py
odoo/addons/stock_secondary_unit_weighing/__manifest__.py
odoo/addons/stock_secondary_unit_weighing/i18n/es.po
odoo/addons/stock_secondary_unit_weighing/i18n/stock_secondary_unit_weighing.pot
odoo/addons/stock_secondary_unit_weighing/models/__init__.py
odoo/addons/stock_secondary_unit_weighing/models/stock_move.py
odoo/addons/stock_secondary_unit_weighing/models/stock_move_line.py
odoo/addons/stock_secondary_unit_weighing/readme/CONTRIBUTORS.md
odoo/addons/stock_secondary_unit_weighing/readme/DESCRIPTION.md
odoo/addons/stock_secondary_unit_weighing/static/description/icon.png
odoo/addons/stock_secondary_unit_weighing/static/description/index.html
odoo/addons/stock_secondary_unit_weighing/views/stock_move_views.xml
odoo_addon_stock_secondary_unit_weighing-15.0.1.0.0.3.dist-info/METADATA
odoo_addon_stock_secondary_unit_weighing-15.0.1.0.0.3.dist-info/WHEEL
odoo_addon_stock_secondary_unit_weighing-15.0.1.0.0.3.dist-info/top_level.txt
odoo_addon_stock_secondary_unit_weighing-15.0.1.0.0.3.dist-info/RECORD
