Metadata-Version: 2.1
Name: odoo-addon-stock_secondary_unit_weighing
Version: 15.0.1.0.0.3
Summary: Show secondary unit info in the weighing assistant
Home-page: https://github.com/OCA/stock-weighing
Author: Tecnativa, Odoo Community Association (OCA)
Author-email: support@odoo-community.org
License: AGPL-3
Classifier: Programming Language :: Python
Classifier: Framework :: Odoo
Classifier: Framework :: Odoo :: 15.0
Classifier: License :: OSI Approved :: GNU Affero General Public License v3
Requires-Python: >=3.8
Requires-Dist: odoo-addon-stock-secondary-unit <15.1dev,>=15.0dev
Requires-Dist: odoo-addon-stock-weighing <15.1dev,>=15.0dev
Requires-Dist: odoo <15.1dev,>=15.0a
